moftransformer/__init__.py
moftransformer/config.py
moftransformer/config_ex.py
moftransformer/predict.py
moftransformer/run.py
moftransformer/test.py
moftransformer/assets/__init__.py
moftransformer/assets/bbs.json
moftransformer/assets/colors.py
moftransformer/assets/topology.json
moftransformer/cli/__init__.py
moftransformer/cli/download.py
moftransformer/cli/install_griday.py
moftransformer/cli/main.py
moftransformer/cli/predict.py
moftransformer/cli/run.py
moftransformer/cli/test.py
moftransformer/cli/uninstall_griday.py
moftransformer/database/__init__.py
moftransformer/datamodules/__init__.py
moftransformer/datamodules/datamodule.py
moftransformer/datamodules/dataset.py
moftransformer/examples/__init__.py
moftransformer/examples/dataset/test_example.json
moftransformer/examples/dataset/train_example.json
moftransformer/examples/dataset/val_example.json
moftransformer/examples/dataset/test/etc+N80+N60+E173+E76.cif
moftransformer/examples/dataset/test/etc+N80+N60+E173+E76.graphdata
moftransformer/examples/dataset/test/etc+N80+N60+E173+E76.grid
moftransformer/examples/dataset/test/etc+N80+N60+E173+E76.griddata16
moftransformer/examples/dataset/total/acs+N270+E33.cif
moftransformer/examples/dataset/total/acs+N270+E33.graphdata
moftransformer/examples/dataset/total/acs+N270+E33.grid
moftransformer/examples/dataset/total/acs+N270+E33.griddata16
moftransformer/examples/dataset/total/etc+N80+N60+E173+E76.cif
moftransformer/examples/dataset/total/etc+N80+N60+E173+E76.graphdata
moftransformer/examples/dataset/total/etc+N80+N60+E173+E76.grid
moftransformer/examples/dataset/total/etc+N80+N60+E173+E76.griddata16
moftransformer/examples/dataset/total/fee+N254+E185.cif
moftransformer/examples/dataset/total/fee+N254+E185.graphdata
moftransformer/examples/dataset/total/fee+N254+E185.grid
moftransformer/examples/dataset/total/fee+N254+E185.griddata16
moftransformer/examples/dataset/total/mok+N109+E146.cif
moftransformer/examples/dataset/total/mok+N109+E146.graphdata
moftransformer-2.2.0.dist-info/METADATA
moftransformer-2.2.0.dist-info/WHEEL
moftransformer-2.2.0.dist-info/entry_points.txt
moftransformer-2.2.0.dist-info/top_level.txt
moftransformer-2.2.0.dist-info/RECORD
