Metadata-Version: 2.1
Name: moftransformer
Version: 2.2.0
Summary: moftransformer
Home-page: https://hspark1212.github.io/MOFTransformer/
Download-URL: https://github.com/hspark1212/MOFTransformer
Author: Yeonghun Kang, Hyunsoo Park
Author-email: dudgns1675@kaist.ac.kr, phs68660888@gmail.com
Requires-Python: >=3.8
Requires-Dist: wget
Requires-Dist: torch <2.0.0
Requires-Dist: pytorch-lightning ==1.7.0
Requires-Dist: numpy <2.0.0
Requires-Dist: torchmetrics <1.0.0,>=0.6.0
Requires-Dist: transformers <4.39.0,>=4.12.5
Requires-Dist: timm >=0.4.12
Requires-Dist: sacred >=0.8.2
Requires-Dist: einops >=0.4.1
Requires-Dist: ase >=3.22.1
Requires-Dist: pymatgen >=2022.0.16
Requires-Dist: matplotlib >=3.5.0
Requires-Dist: seaborn >=0.12.0
Requires-Dist: ipympl >=0.9.2
Requires-Dist: pandas
Requires-Dist: tqdm
Requires-Dist: google-auth
Requires-Dist: jupyter-client
Requires-Dist: smmap <6
Requires-Dist: emmet-core
Requires-Dist: scikit-learn
Provides-Extra: docs
Requires-Dist: sphinx ; extra == 'docs'
Requires-Dist: livereload ; extra == 'docs'
Requires-Dist: myst-parser ; extra == 'docs'
